.coveragerc
AUTHORS
ChangeLog
LICENSE
README.md
doc-requirements.txt
requirements.txt
server-setup.md
setup.cfg
setup.py
test-requirements.txt
tox.ini
docs/.nojekyll
docs/data_feeds.html
docs/datasets.html
docs/genindex.html
docs/index.html
docs/models.html
docs/modules.html
docs/monitors.html
docs/objects.inv
docs/parameter_group.html
docs/py-modindex.html
docs/schedules.html
docs/sconce.data_feeds.html
docs/sconce.datasets.html
docs/sconce.html
docs/sconce.models.html
docs/sconce.models.layers.html
docs/sconce.monitors.html
docs/sconce.schedules.html
docs/sconce.trainers.html
docs/search.html
docs/searchindex.js
docs/trainers.html
docs/transforms.html
docs/_modules/index.html
docs/_modules/sconce/parameter_group.html
docs/_modules/sconce/trainer.html
docs/_modules/sconce/transforms.html
docs/_modules/sconce/utils.html
docs/_modules/sconce/data_feeds/base.html
docs/_modules/sconce/data_feeds/image.html
docs/_modules/sconce/data_feeds/multi_class_image.html
docs/_modules/sconce/data_feeds/single_class_image.html
docs/_modules/sconce/datasets/csv_image_folder.html
docs/_modules/sconce/datasets/simple_dots.html
docs/_modules/sconce/models/base.html
docs/_modules/sconce/models/basic_autoencoder.html
docs/_modules/sconce/models/basic_classifier.html
docs/_modules/sconce/models/basic_convolutional_autoencoder.html
docs/_modules/sconce/models/multilayer_perceptron.html
docs/_modules/sconce/models/variational_autoencoder.html
docs/_modules/sconce/models/wide_resnet_image_classifier.html
docs/_modules/sconce/models/layers/convolution2d_layer.html
docs/_modules/sconce/models/layers/fully_connected_layer.html
docs/_modules/sconce/monitors/base.html
docs/_modules/sconce/monitors/dataframe_monitor.html
docs/_modules/sconce/monitors/losswise_monitor.html
docs/_modules/sconce/monitors/ringbuffer_monitor.html
docs/_modules/sconce/monitors/stdout_monitor.html
docs/_modules/sconce/schedules/base.html
docs/_modules/sconce/schedules/cosine.html
pytorch_sconce.egg-info/PKG-INFO
pytorch_sconce.egg-info/SOURCES.txt
pytorch_sconce.egg-info/dependency_links.txt
pytorch_sconce.egg-info/not-zip-safe
pytorch_sconce.egg-info/pbr.json
pytorch_sconce.egg-info/requires.txt
pytorch_sconce.egg-info/top_level.txt
