Metadata-Version: 1.2
Name: pytorch-sconce
Version: 1.4.0
Summary: A library for training pytorch models
Home-page: UNKNOWN
Author: David Morton
Author-email: davidlmorton@gmail.com
License: UNKNOWN
Download-URL: https://github.com/davidlmorton/pytorch-sconce/archive/1.4.0.tar.gz
Project-URL: Documentation, https://davidlmorton.github.io/pytorch-sconce
Project-URL: Source Code, https://github.com/davidlmorton/pytorch-sconce
Platform: UNKNOWN
